dearmor/__init__.py
dearmor/__main__.py
dearmor/code.py
dearmor/Release/dearmor.dll
dearmor-0.3.1.dist-info/LICENSE
dearmor-0.3.1.dist-info/METADATA
dearmor-0.3.1.dist-info/WHEEL
dearmor-0.3.1.dist-info/entry_points.txt
dearmor-0.3.1.dist-info/top_level.txt
dearmor-0.3.1.dist-info/RECORD
