Metadata-Version: 2.1
Name: dearmor
Version: 0.3.1
Summary: Deobfuscate pyarmor files
Home-page: https://github.com/ErezAmihud/dearmor
Author: Erez Amihud
Author-email: erezamihud@gmail.com
License: Apache-2.0
License-File: LICENSE
Requires-Dist: pyinjector
Requires-Dist: psutil
Provides-Extra: test
Requires-Dist: pytest ; extra == 'test'
Requires-Dist: pytest-timeout ; extra == 'test'
Requires-Dist: pyarmor ; extra == 'test'
